quickshear.py
quickshear-1.2.0.dist-info/METADATA
quickshear-1.2.0.dist-info/WHEEL
quickshear-1.2.0.dist-info/entry_points.txt
quickshear-1.2.0.dist-info/licenses/LICENSE
quickshear-1.2.0.dist-info/RECORD
