Metadata-Version: 2.1
Name: quickshear
Version: 1.2.0
Summary: Quickshear Defacing for Neuroimages
Project-URL: Homepage, https://github.com/nipy/quickshear
Author: Nakeisha Schimke, John Hale
Maintainer: Christopher J. Markiewicz
Maintainer-email: neuroimaging@python.org
License: Copyright (c) 2011, Nakeisha Schimke. All rights reserved.
License-File: LICENSE
Keywords: neuroimaging,neuroscience
Classifier: Development Status :: 5 - Production/Stable
Classifier: Intended Audience :: Science/Research
Classifier: License :: OSI Approved :: BSD License
Classifier: Programming Language :: Python :: 2
Classifier: Programming Language :: Python :: 2.7
Classifier: Programming Language :: Python :: 3
Classifier: Programming Language :: Python :: 3.7
Classifier: Programming Language :: Python :: 3.8
Classifier: Programming Language :: Python :: 3.9
Classifier: Programming Language :: Python :: 3.10
Classifier: Programming Language :: Python :: 3.11
Classifier: Topic :: Software Development :: Build Tools
Requires-Dist: nibabel
Requires-Dist: numpy
